deployer/__init__.py
deployer/constants.py
deployer/exceptions.py
deployer/main.py
deployer/upload.py
deployer/utils.py
stumptown_deployer-0.2.6.dist-info/LICENSE
stumptown_deployer-0.2.6.dist-info/METADATA
stumptown_deployer-0.2.6.dist-info/WHEEL
stumptown_deployer-0.2.6.dist-info/entry_points.txt
stumptown_deployer-0.2.6.dist-info/top_level.txt
stumptown_deployer-0.2.6.dist-info/RECORD
