Metadata-Version: 2.1
Name: stumptown-deployer
Version: 0.2.6
Summary: Deploying static Stumptown sites
Home-page: https://github.com/mdn/stumptown-deployer
Author: Mozilla MDN
License: MPL 2.0
Keywords: git github s3 boto3 stumptown mdn
Platform: UNKNOWN
Classifier: Programming Language :: Python
Classifier: Programming Language :: Python :: 3
Classifier: Programming Language :: Python :: Implementation :: CPython
Classifier: License :: OSI Approved :: Mozilla Public License 2.0 (MPL 2.0)
Requires-Dist: boto3
Requires-Dist: click
Requires-Dist: PyGithub
Requires-Dist: GitPython
Requires-Dist: python-decouple
Provides-Extra: dev
Requires-Dist: black (==19.3b0) ; extra == 'dev'
Requires-Dist: flake8 (==3.7.8) ; extra == 'dev'
Requires-Dist: therapist ; extra == 'dev'
